private_attribute.cp311-win_amd64.pyd
private_attribute.pyi
private_attribute_cpp-1.2.10.dist-info/METADATA
private_attribute_cpp-1.2.10.dist-info/WHEEL
private_attribute_cpp-1.2.10.dist-info/top_level.txt
private_attribute_cpp-1.2.10.dist-info/RECORD
