Metadata-Version: 2.4
Name: private_attribute_cpp
Version: 1.2.10
Summary: A Python package that provides a way to define private attributes in C++ implementation.
Home-page: https://github.com/Locked-chess-official/private_attribute_cpp
Author: HuangHaoHua
Author-email: 13140752715@example.com
License: MIT
Dynamic: author
Dynamic: author-email
Dynamic: description
Dynamic: description-content-type
Dynamic: home-page
Dynamic: license
Dynamic: summary
